Metadata-Version: 2.1
Name: novigi-airflow
Version: 1.0.0
Summary: Novigi Custom Airflow Operators
Home-page: UNKNOWN
Author: Novigi
Author-email: integration@novigi.com.au
License: MIT
Platform: UNKNOWN
License-File: LICENSE.txt
